{
  "id": 14587,
  "first_name": "Jenna",
  "last_name": "Hovi",
  "election_number": 485,
  "party_id": 5,
  "image": "kuvat/akv2025/14587/56ff3cef-0bdd-42b4-b3a3-5f8bf138d162",
  "constituency_id": 25,
  "video": null,
  "video_aspect": null,
  "video_description_fi": null,
  "video_description_sv": null,
  "video_description_en": null,
  "video_description_ru": null,
  "video_description_sme": null,
  "video_description_ara": null,
  "candidate_hidden": null,
  "info": {
    "left_right_axis": {
      "id": 44,
      "background_info_id": 10,
      "name_fi": "Hieman vasemmalle",
      "name_sv": "Lite till vänster",
      "name_en": "Slightly to the left",
      "name_ru": "Немного слева",
      "name_sme": "Vehá gurut guvlui",
      "name_ara": "أميل إلى اليسار",
      "target_value": -1,
      "name_ukr": null,
      "name_som": null
    },
    "election_promise_3": {
      "fi": "Kokonaisvaltaisen hyvinvoinnin edistämistä!\n\n- Itsetuntemuksen ja hyväntahtoisuuden asialla.",
      "se": null,
      "en": null,
      "ru": null,
      "sme": null,
      "ara": null,
      "ukr": null,
      "som": null
    },
    "age": 1997,
    "language_skills": [
      {
        "fi": "suomi",
        "se": "finska",
        "en": "Finnish",
        "ru": "финский",
        "sme": "suomagiella",
        "ara": "الفنلندية"
      },
      {
        "fi": "englanti",
        "se": "engelska",
        "en": "English",
        "ru": "английский",
        "sme": "eaŋgalsgiella",
        "ara": "الإنجليزية"
      }
    ],
    "education": {
      "id": 52,
      "background_info_id": 16,
      "name_fi": "alempi korkeakoulututkinto",
      "name_sv": "lägre högskoleexamen",
      "name_en": "Bachelors degree",
      "name_ru": "первая ступень высшего образования (бакалавриат)",
      "name_sme": "vuolit allaskuvladutkkus",
      "name_ara": "درجة البكالوريوس",
      "target_value": 4,
      "name_ukr": "перший ступінь вищої освіти (бакалаврат)",
      "name_som": null
    },
    "gender": {
      "id": 18,
      "background_info_id": 6,
      "name_fi": "nainen",
      "name_sv": "kvinna",
      "name_en": "woman",
      "name_ru": "Женский",
      "name_sme": "nisson",
      "name_ara": "امرأة",
      "target_value": null,
      "name_ukr": "Жіноча",
      "name_som": "naag"
    },
    "lifevalues": {
      "fi": "Kokonaisvaltainen hyvinvointi\nVastuullisuus & vapaus\nYhteisöllisyys & välittäminen\nElinikäinen oppiminen\nYlisukupolvisuus & kohtuullisuus",
      "se": null,
      "en": null,
      "ru": null,
      "sme": null,
      "ara": null,
      "ukr": null,
      "som": null
    },
    "election_promise_2": {
      "fi": "Kohtuuhintaista ja viihtyisää asumista!\n\n- Moninaista ja saavutettavaa asumista lähellä palveluja ja luontoa.",
      "se": null,
      "en": null,
      "ru": null,
      "sme": null,
      "ara": null,
      "ukr": null,
      "som": null
    },
    "language": {
      "id": 22,
      "background_info_id": 8,
      "name_fi": "suomi",
      "name_sv": "Finska",
      "name_en": "Finnish",
      "name_ru": "финский",
      "name_sme": "suomagiella",
      "name_ara": "الفنلندية",
      "target_value": null,
      "name_ukr": "фінська",
      "name_som": "af-finnish"
    },
    "homepage_url": "https://www.linkedin.com/in/jenna-h-9b8706141/",
    "instagram_url": "https://www.instagram.com/j.ve.h?igsh=MWoyZzRzenN2ang3dA==",
    "municipality_fix": {
      "fi": "Asumisen kustannukset\n\nYksinäisyys\n\nHyvinvoinnin ylläpitäminen ",
      "se": null,
      "en": null,
      "ru": null,
      "sme": null,
      "ara": null,
      "ukr": null,
      "som": null
    },
    "representative_other": {
      "fi": "Ei ole tällä hetkellä.",
      "se": null,
      "en": null,
      "ru": null,
      "sme": null,
      "ara": null,
      "ukr": null,
      "som": null
    },
    "liberal_conservative_axis": {
      "id": 2,
      "background_info_id": 2,
      "name_fi": "Liberaali",
      "name_sv": "Liberal",
      "name_en": "Liberal",
      "name_ru": "Либерал",
      "name_sme": "Liberála",
      "name_ara": "ليبرالي",
      "target_value": -2,
      "name_ukr": null,
      "name_som": null
    },
    "municipality": "091",
    "language_other": {
      "fi": null,
      "se": null,
      "en": null,
      "ru": null,
      "sme": null,
      "ara": null,
      "ukr": null,
      "som": null
    },
    "election_promise_1": {
      "fi": "Ponnistelu yksinäisyyttä vastaan ja yhteisöllisyyden puolesta!\n\n- Myötätuntontoista, osallistavaa ja  voimaannuttavaa vastuuta sekä tukea.",
      "se": null,
      "en": null,
      "ru": null,
      "sme": null,
      "ara": null,
      "ukr": null,
      "som": null
    },
    "representative": [
      {
        "fi": "ei mikään näistä",
        "se": "inget av dessa",
        "en": "none of the above",
        "ru": null,
        "sme": null,
        "ara": null
      }
    ]
  }
}
