{
  "id": 1408,
  "first_name": "Outi",
  "last_name": "Paulig",
  "election_number": 166,
  "party_id": 7,
  "image": "kuvat/akv2025/1408/bb202957-82f9-42ef-8454-ce276ef93559",
  "constituency_id": 25,
  "video": null,
  "video_aspect": null,
  "video_description_fi": null,
  "video_description_sv": null,
  "video_description_en": null,
  "video_description_ru": null,
  "video_description_sme": null,
  "video_description_ara": null,
  "candidate_hidden": null,
  "info": {
    "left_right_axis": {
      "id": 42,
      "background_info_id": 10,
      "name_fi": "Vahvasti vasemmalle",
      "name_sv": "Långt till vänster",
      "name_en": "Strongly on the left",
      "name_ru": "С самого левого края",
      "name_sme": "Nannosit gurut guvlui",
      "name_ara": "أقصى اليسار",
      "target_value": -3,
      "name_ukr": null,
      "name_som": null
    },
    "election_promise_3": {
      "fi": "Teen parhaani, jotta helsinkiläiset voivat nauttia lähiluonnosta. Tämä koskee kaikkia kaupunkilaisia, myös hitaammin liikkuvia sekä liikkumis- ja aistirajoitteisia. Kevyen liikenteen väylillä pitää voida kulkea turvallisesti. Seniorien mahdollisuuksia käyttää kaupunkipyöriä tulee edistää ja ikäihmisten pitää voida uskaltaa ajella lähiluonnon ääreen.  ",
      "se": null,
      "en": null,
      "ru": null,
      "sme": null,
      "ara": null,
      "ukr": null,
      "som": null
    },
    "age": 1958,
    "language_skills": [
      {
        "fi": "suomi",
        "se": "finska",
        "en": "Finnish",
        "ru": "финский",
        "sme": "suomagiella",
        "ara": "الفنلندية"
      },
      {
        "fi": "ruotsi",
        "se": "svenska",
        "en": "Swedish",
        "ru": "шведский",
        "sme": "ruoŧagiella",
        "ara": "السويدية"
      },
      {
        "fi": "englanti",
        "se": "engelska",
        "en": "English",
        "ru": "английский",
        "sme": "eaŋgalsgiella",
        "ara": "الإنجليزية"
      },
      {
        "fi": "saksa",
        "se": "tyska",
        "en": "German",
        "ru": "немецкий",
        "sme": "duiskkagiella",
        "ara": "الألمانية"
      }
    ],
    "education": {
      "id": 53,
      "background_info_id": 16,
      "name_fi": "ylempi korkeakoulututkinto",
      "name_sv": "högre högskoleexamen",
      "name_en": "Masters degree",
      "name_ru": "вторая ступень высшего образования (магистратура)",
      "name_sme": "bajit allaskuvladutkkus",
      "name_ara": "درجة الماجستير",
      "target_value": 5,
      "name_ukr": "другий ступінь вищої освіти (магістратура)",
      "name_som": null
    },
    "gender": {
      "id": 18,
      "background_info_id": 6,
      "name_fi": "nainen",
      "name_sv": "kvinna",
      "name_en": "woman",
      "name_ru": "Женский",
      "name_sme": "nisson",
      "name_ara": "امرأة",
      "target_value": null,
      "name_ukr": "Жіноча",
      "name_som": "naag"
    },
    "lifevalues": {
      "fi": "Inhimillisyys.\nOikeudenmukaisuus.\nYhdenvertaisuus.\nRehellisyys.\nVastuullisuus.",
      "se": null,
      "en": null,
      "ru": null,
      "sme": null,
      "ara": null,
      "ukr": null,
      "som": null
    },
    "election_promise_2": {
      "fi": "Teen parhaani edistääkseni yhteisöllistä ja viihtyisää Helsinkiä. Se on paras tae kaupungin elinvoimalle ja turvallisuudelle.",
      "se": null,
      "en": null,
      "ru": null,
      "sme": null,
      "ara": null,
      "ukr": null,
      "som": null
    },
    "language": {
      "id": 22,
      "background_info_id": 8,
      "name_fi": "suomi",
      "name_sv": "Finska",
      "name_en": "Finnish",
      "name_ru": "финский",
      "name_sme": "suomagiella",
      "name_ara": "الفنلندية",
      "target_value": null,
      "name_ukr": "фінська",
      "name_som": "af-finnish"
    },
    "facebook_url": "https://www.facebook.com/outi.paulig",
    "instagram_url": "https://instagram.com/outipaulig",
    "X_url": null,
    "municipality_fix": {
      "fi": "Kaikilla ihmisillä tulee olla yhdenvertaiset mahdollisuudet hyvään elämään.",
      "se": null,
      "en": null,
      "ru": null,
      "sme": null,
      "ara": null,
      "ukr": null,
      "som": null
    },
    "representative_other": {
      "fi": "Kaupunkiympäristölautakunnan ympäristö- ja lupajaoston jäsen.",
      "se": null,
      "en": null,
      "ru": null,
      "sme": null,
      "ara": null,
      "ukr": null,
      "som": null
    },
    "liberal_conservative_axis": {
      "id": 1,
      "background_info_id": 2,
      "name_fi": "Vahvasti liberaali",
      "name_sv": "Mycket liberal",
      "name_en": "Strongly liberal",
      "name_ru": "В значительной степени либерал",
      "name_sme": "Nannosit liberála",
      "name_ara": "ليبرالي جدا",
      "target_value": -3,
      "name_ukr": null,
      "name_som": null
    },
    "municipality": "091",
    "election_promise_1": {
      "fi": "Teen parhaani edistääkseni yhdenvertaisuutta helsinkiläisten kesken. Esimerkiksi, jokaisella pitää varaa HSL:n lippuun.",
      "se": null,
      "en": null,
      "ru": null,
      "sme": null,
      "ara": null,
      "ukr": null,
      "som": null
    },
    "representative": [
      {
        "fi": "ei mikään näistä",
        "se": "inget av dessa",
        "en": "none of the above",
        "ru": null,
        "sme": null,
        "ara": null
      }
    ],
    "political_experience": {
      "fi": "Kaupunkiympäristölautakunnan ympäristö- ja lupajaoston jäsen. Liikuntalautakunnan varajäsen 2013-2017",
      "se": null,
      "en": null,
      "ru": null,
      "sme": null,
      "ara": null,
      "ukr": null,
      "som": null
    }
  }
}
