{
  "id": 508,
  "first_name": "Samuli",
  "last_name": "Juntunen",
  "election_number": 562,
  "party_id": 2,
  "image": "kuvat/akv2025/508/1088241a-32b4-4bf0-ad13-3427f81988e7",
  "constituency_id": 25,
  "video": null,
  "video_aspect": null,
  "video_description_fi": null,
  "video_description_sv": null,
  "video_description_en": null,
  "video_description_ru": null,
  "video_description_sme": null,
  "video_description_ara": null,
  "candidate_hidden": null,
  "info": {
    "left_right_axis": {
      "id": 45,
      "background_info_id": 10,
      "name_fi": "En vasemmalle enkä oikealle",
      "name_sv": "Varken vänster eller höger",
      "name_en": "Neither to the right or the left",
      "name_ru": "Ни слева, ни справа",
      "name_sme": "In gurut inge olgeš guvlui",
      "name_ara": "لا إلى اليسار ولا إلى اليمين",
      "target_value": 0,
      "name_ukr": null,
      "name_som": null
    },
    "election_promise_3": {
      "fi": "Ajan valtuustossa erityisesti kulttuurialan ihmisten etuja ja asiaa, jos sinne asti pääsen.",
      "se": null,
      "en": null,
      "ru": null,
      "sme": null,
      "ara": null,
      "ukr": null,
      "som": null
    },
    "age": 1969,
    "language_skills": [
      {
        "fi": "suomi",
        "se": "finska",
        "en": "Finnish",
        "ru": "финский",
        "sme": "suomagiella",
        "ara": "الفنلندية"
      },
      {
        "fi": "ruotsi",
        "se": "svenska",
        "en": "Swedish",
        "ru": "шведский",
        "sme": "ruoŧagiella",
        "ara": "السويدية"
      },
      {
        "fi": "englanti",
        "se": "engelska",
        "en": "English",
        "ru": "английский",
        "sme": "eaŋgalsgiella",
        "ara": "الإنجليزية"
      },
      {
        "fi": "saksa",
        "se": "tyska",
        "en": "German",
        "ru": "немецкий",
        "sme": "duiskkagiella",
        "ara": "الألمانية"
      },
      {
        "fi": "espanja",
        "se": "spanska",
        "en": "Spanish",
        "ru": "испанский",
        "sme": "spánskkagiella",
        "ara": "الإسبانية"
      },
      {
        "fi": "italia",
        "se": "italienska",
        "en": "Italian",
        "ru": "итальянский",
        "sme": "italiagiella",
        "ara": "الإيطالية"
      },
      {
        "fi": "viro",
        "se": "estniska",
        "en": "Estonian",
        "ru": "эстонский",
        "sme": "esttegiella",
        "ara": "الإستونية"
      },
      {
        "fi": "arabia",
        "se": "arabiska",
        "en": "Arabic",
        "ru": "арабский",
        "sme": null,
        "ara": "العربية"
      },
      {
        "fi": "somali",
        "se": "somaliska",
        "en": "Somali",
        "ru": "сомалийский",
        "sme": null,
        "ara": "الصومالية"
      }
    ],
    "education": {
      "id": 53,
      "background_info_id": 16,
      "name_fi": "ylempi korkeakoulututkinto",
      "name_sv": "högre högskoleexamen",
      "name_en": "Masters degree",
      "name_ru": "вторая ступень высшего образования (магистратура)",
      "name_sme": "bajit allaskuvladutkkus",
      "name_ara": "درجة الماجستير",
      "target_value": 5,
      "name_ukr": "другий ступінь вищої освіти (магістратура)",
      "name_som": null
    },
    "gender": {
      "id": 19,
      "background_info_id": 6,
      "name_fi": "mies",
      "name_sv": "man",
      "name_en": "man",
      "name_ru": "Мужской",
      "name_sme": "almmái",
      "name_ara": "رجل",
      "target_value": null,
      "name_ukr": "Чоловіча",
      "name_som": "nin"
    },
    "lifevalues": {
      "fi": "Itsenäisyys, vapaus, suoraselkäisyys, oikeudenmukaisuus, tasapuolisuus.",
      "se": null,
      "en": null,
      "ru": null,
      "sme": null,
      "ara": null,
      "ukr": null,
      "som": null
    },
    "election_promise_2": {
      "fi": "Taistelen järjetöntä rahan haaskausta vastaan sekä yksityisesti että yhteisöllisesti.",
      "se": null,
      "en": null,
      "ru": null,
      "sme": null,
      "ara": null,
      "ukr": null,
      "som": null
    },
    "language": {
      "id": 22,
      "background_info_id": 8,
      "name_fi": "suomi",
      "name_sv": "Finska",
      "name_en": "Finnish",
      "name_ru": "финский",
      "name_sme": "suomagiella",
      "name_ara": "الفنلندية",
      "target_value": null,
      "name_ukr": "фінська",
      "name_som": "af-finnish"
    },
    "facebook_url": "https://www.facebook.com/SamuLibJuntunen",
    "instagram_url": "https://www.instagram.com/samulijuntunen?igsh=MXU0bWs3MWRkY2ZsZg==",
    "X_url": "https://x.com/SamuLibJuntunen?t=8ozVVcE7_-ZxWAYpnAzU_Q&s=09",
    "tiktok_url": "https://www.tiktok.com/@samulijuntunen",
    "municipality_fix": {
      "fi": "Julkisen rahan käyttö, ensimmäisenä. Toissijaisesti julkiset palvelut, jotka ovat joissain tapauksissa pahasti puutteellisia. Nämä ovat tietysti läheisesti kytköksissä toisiinsa.",
      "se": null,
      "en": null,
      "ru": null,
      "sme": null,
      "ara": null,
      "ukr": null,
      "som": null
    },
    "representative_other": {
      "fi": "Ei mitään.",
      "se": null,
      "en": null,
      "ru": null,
      "sme": null,
      "ara": null,
      "ukr": null,
      "som": null
    },
    "liberal_conservative_axis": {
      "id": 2,
      "background_info_id": 2,
      "name_fi": "Liberaali",
      "name_sv": "Liberal",
      "name_en": "Liberal",
      "name_ru": "Либерал",
      "name_sme": "Liberála",
      "name_ara": "ليبرالي",
      "target_value": -2,
      "name_ukr": null,
      "name_som": null
    },
    "municipality": "091",
    "election_promise_1": {
      "fi": "Ajan poliittisen ja taloudellisen vapauden sekä mahdollisimman vähäisen yhteiskunnallisen holhouksen asiaa, puolueeni johtavien periaatteiden mukaisesti.",
      "se": null,
      "en": null,
      "ru": null,
      "sme": null,
      "ara": null,
      "ukr": null,
      "som": null
    },
    "representative": [
      {
        "fi": "ei mikään näistä",
        "se": "inget av dessa",
        "en": "none of the above",
        "ru": null,
        "sme": null,
        "ara": null
      }
    ]
  }
}
