{
  "id": 16548,
  "first_name": "Björn",
  "last_name": "Månsson",
  "election_number": 649,
  "party_id": 8,
  "image": "kuvat/akv2025/16548/de218560-5c5c-4ba6-bc9e-7dc1262e5830",
  "constituency_id": 25,
  "video": null,
  "video_aspect": null,
  "answers": {
    "81": {
      "answer": 1,
      "options_answer": null,
      "explanation_fi": null,
      "explanation_sv": "På orter som Helsingfors med ca 5 % svensk befolkningsandel och en spridd svensk befolkning krävs det även små skolor för att tillfredsställa behovet av närskolor, sktuellt exempel: Sockenbacka!",
      "explanation_en": null,
      "explanation_ru": null,
      "explanation_sme": null,
      "explanation_ara": null,
      "explanation_ukr": null,
      "explanation_som": null
    },
    "82": {
      "answer": 5,
      "options_answer": null,
      "explanation_fi": null,
      "explanation_sv": "Ju tidigare undervisningen i språk inleds, desto bättre resultat. Gäller alla språk.",
      "explanation_en": null,
      "explanation_ru": null,
      "explanation_sme": null,
      "explanation_ara": null,
      "explanation_ukr": null,
      "explanation_som": null
    },
    "83": {
      "answer": 5,
      "options_answer": null,
      "explanation_fi": null,
      "explanation_sv": "I mindre grupper uppnås bättre undervisningsresultat.",
      "explanation_en": null,
      "explanation_ru": null,
      "explanation_sme": null,
      "explanation_ara": null,
      "explanation_ukr": null,
      "explanation_som": null
    },
    "84": {
      "answer": 2,
      "options_answer": null,
      "explanation_fi": null,
      "explanation_sv": "Det ska alltid finnas ett vegetariskt alternativ, men inhemska köttprodukter bör inte bannlysas.",
      "explanation_en": null,
      "explanation_ru": null,
      "explanation_sme": null,
      "explanation_ara": null,
      "explanation_ukr": null,
      "explanation_som": null
    },
    "85": {
      "answer": 4,
      "options_answer": null,
      "explanation_fi": null,
      "explanation_sv": "Det finns ju olika teorier om hur nyttigt det är för barn att stanna hemma respektive delta i småbarnsfostran. Själv lutar jag åt småbarnsgfostran, från 3 års ålder Men för många mindrebemedlade var slopandet av Helsingforstillägget problematiskt.",
      "explanation_en": null,
      "explanation_ru": null,
      "explanation_sme": null,
      "explanation_ara": null,
      "explanation_ukr": null,
      "explanation_som": null
    },
    "86": {
      "answer": 4,
      "options_answer": null,
      "explanation_fi": null,
      "explanation_sv": "Julsånger och -psalmer hör, liksom Den blomstertid på vårfester, till vårt kulturarv.,\n\n\n\n\n\n",
      "explanation_en": null,
      "explanation_ru": null,
      "explanation_sme": null,
      "explanation_ara": null,
      "explanation_ukr": null,
      "explanation_som": null
    },
    "87": {
      "answer": 4,
      "options_answer": null,
      "explanation_fi": null,
      "explanation_sv": "Kunde vara värt att pröva, då barnfamijer nu snarare flyttar ut.",
      "explanation_en": null,
      "explanation_ru": null,
      "explanation_sme": null,
      "explanation_ara": null,
      "explanation_ukr": null,
      "explanation_som": null
    },
    "88": {
      "answer": 4,
      "options_answer": null,
      "explanation_fi": null,
      "explanation_sv": "Som utgångspunkt ja, men undersökningar har visat att många vore villiga att höja skatterna för att kunna bibehålla servicenivån i t.ex. skolor och dagvård och för de tjänster för de äldre som inte efter vårdrefomen finansieras av staten.",
      "explanation_en": null,
      "explanation_ru": null,
      "explanation_sme": null,
      "explanation_ara": null,
      "explanation_ukr": null,
      "explanation_som": null
    },
    "89": {
      "answer": 2,
      "options_answer": null,
      "explanation_fi": null,
      "explanation_sv": "Det kan hända att vi i framtiden måste hitta nya intäktskällor för att kommunerna ska kunna upprätthålla en god servicenivå",
      "explanation_en": null,
      "explanation_ru": null,
      "explanation_sme": null,
      "explanation_ara": null,
      "explanation_ukr": null,
      "explanation_som": null
    },
    "90": {
      "answer": 4,
      "options_answer": null,
      "explanation_fi": null,
      "explanation_sv": "Om möjligt, men privata bolag kan och ska komplettera, t.ex. med köptjänster och servicesedlar.",
      "explanation_en": null,
      "explanation_ru": null,
      "explanation_sme": null,
      "explanation_ara": null,
      "explanation_ukr": null,
      "explanation_som": null
    },
    "91": {
      "answer": 1,
      "options_answer": null,
      "explanation_fi": null,
      "explanation_sv": "Inte aktuellt för Helsingfors, men ute i regionerna må kommunerna bestämma själva om servicen är nödvändig.",
      "explanation_en": null,
      "explanation_ru": null,
      "explanation_sme": null,
      "explanation_ara": null,
      "explanation_ukr": null,
      "explanation_som": null
    },
    "92": {
      "answer": 2,
      "options_answer": null,
      "explanation_fi": null,
      "explanation_sv": "Inte aktuellt i Helsingfors, men personlig betjäning kan främja möjligheterna att syselsätta arbetslösa.",
      "explanation_en": null,
      "explanation_ru": null,
      "explanation_sme": null,
      "explanation_ara": null,
      "explanation_ukr": null,
      "explanation_som": null
    },
    "93": {
      "answer": 4,
      "options_answer": null,
      "explanation_fi": null,
      "explanation_sv": "Bara om det är absolut nödvändigt.",
      "explanation_en": null,
      "explanation_ru": null,
      "explanation_sme": null,
      "explanation_ara": null,
      "explanation_ukr": null,
      "explanation_som": null
    },
    "94": {
      "answer": 5,
      "options_answer": null,
      "explanation_fi": null,
      "explanation_sv": "Det har vi redan gjort, inom ramen för våra resurser, och bör fortsätta med det och stärka det. Kultur är en omistlig del av en hälsosam vardagskost.",
      "explanation_en": null,
      "explanation_ru": null,
      "explanation_sme": null,
      "explanation_ara": null,
      "explanation_ukr": null,
      "explanation_som": null
    },
    "95": {
      "answer": 4,
      "options_answer": null,
      "explanation_fi": null,
      "explanation_sv": "I mån av möjlighet, såsom hittills, men bibliotekspersonalens betjäning är guld värd.",
      "explanation_en": null,
      "explanation_ru": null,
      "explanation_sme": null,
      "explanation_ara": null,
      "explanation_ukr": null,
      "explanation_som": null
    },
    "96": {
      "answer": 5,
      "options_answer": null,
      "explanation_fi": null,
      "explanation_sv": "Absolut! Alla parter vinner på en effektiv integrering!",
      "explanation_en": null,
      "explanation_ru": null,
      "explanation_sme": null,
      "explanation_ara": null,
      "explanation_ukr": null,
      "explanation_som": null
    },
    "97": {
      "answer": 5,
      "options_answer": null,
      "explanation_fi": null,
      "explanation_sv": "Det är en stark symbolisk handling, som inte ens kostar särskilt mycket.",
      "explanation_en": null,
      "explanation_ru": null,
      "explanation_sme": null,
      "explanation_ara": null,
      "explanation_ukr": null,
      "explanation_som": null
    },
    "98": {
      "answer": 5,
      "options_answer": null,
      "explanation_fi": null,
      "explanation_sv": "Vi har inte särskilt glest bebyggda omåden i Helsingfors. Också Östersundom kommer att bebyggas i en nära framtid.",
      "explanation_en": null,
      "explanation_ru": null,
      "explanation_sme": null,
      "explanation_ara": null,
      "explanation_ukr": null,
      "explanation_som": null
    },
    "99": {
      "answer": 5,
      "options_answer": null,
      "explanation_fi": null,
      "explanation_sv": "Vi ska inte skövla Centralparken eller andra återstående skogsområden i Helsingfors.",
      "explanation_en": null,
      "explanation_ru": null,
      "explanation_sme": null,
      "explanation_ara": null,
      "explanation_ukr": null,
      "explanation_som": null
    },
    "100": {
      "answer": 1,
      "options_answer": null,
      "explanation_fi": null,
      "explanation_sv": "I Helsingfors har vi nog råd att säga nej till miljöskadlig näringsverksamhet.,",
      "explanation_en": null,
      "explanation_ru": null,
      "explanation_sme": null,
      "explanation_ara": null,
      "explanation_ukr": null,
      "explanation_som": null
    },
    "101": {
      "answer": 1,
      "options_answer": null,
      "explanation_fi": null,
      "explanation_sv": "Också Helsingfors invånare har rätt till närnatur.",
      "explanation_en": null,
      "explanation_ru": null,
      "explanation_sme": null,
      "explanation_ara": null,
      "explanation_ukr": null,
      "explanation_som": null
    },
    "102": {
      "answer": 5,
      "options_answer": null,
      "explanation_fi": null,
      "explanation_sv": "Helsingfors är på god väg, och vi behöver inget totalförbud mot förbränningsmotorer. Övergången till elbilar kan främjas med fler laddningsstationer,",
      "explanation_en": null,
      "explanation_ru": null,
      "explanation_sme": null,
      "explanation_ara": null,
      "explanation_ukr": null,
      "explanation_som": null
    },
    "103": {
      "answer": 5,
      "options_answer": null,
      "explanation_fi": null,
      "explanation_sv": "Vi behöver fler händer och hjärnor, i bl.a, vården, kollektivtrafiken och innoverande företag. ",
      "explanation_en": null,
      "explanation_ru": null,
      "explanation_sme": null,
      "explanation_ara": null,
      "explanation_ukr": null,
      "explanation_som": null
    },
    "104": {
      "answer": 1,
      "options_answer": null,
      "explanation_fi": null,
      "explanation_sv": "En effektiv integration gynnar både invandrarna och det övriga samhället.",
      "explanation_en": null,
      "explanation_ru": null,
      "explanation_sme": null,
      "explanation_ara": null,
      "explanation_ukr": null,
      "explanation_som": null
    },
    "105": {
      "answer": 1,
      "options_answer": null,
      "explanation_fi": "Varför i hela världen skulle vi göra det? Kvotflyktingarna tas emot från flyktingläger, och särskilt barnen hör till de mest utsatta, i akut behov av en trygg fristad. ",
      "explanation_sv": null,
      "explanation_en": null,
      "explanation_ru": null,
      "explanation_sme": null,
      "explanation_ara": null,
      "explanation_ukr": null,
      "explanation_som": null
    },
    "238": {
      "answer": 1,
      "options_answer": null,
      "explanation_fi": null,
      "explanation_sv": "Det är inte nödvändigt, då elbilarnas andel av bilparken ändå hela tiden växer, och det vore socialt orättvist så länge elbilar är dyrare.",
      "explanation_en": null,
      "explanation_ru": null,
      "explanation_sme": null,
      "explanation_ara": null,
      "explanation_ukr": null,
      "explanation_som": null
    },
    "239": {
      "answer": 5,
      "options_answer": null,
      "explanation_fi": null,
      "explanation_sv": "Extrema rörelser som sprider antitolerant ideologi har ingen plats i vår huvudstad.",
      "explanation_en": null,
      "explanation_ru": null,
      "explanation_sme": null,
      "explanation_ara": null,
      "explanation_ukr": null,
      "explanation_som": null
    },
    "240": {
      "answer": 1,
      "options_answer": null,
      "explanation_fi": null,
      "explanation_sv": "Vi slopade hälsocentralsavgiften dels för att kompensera för de höga levnadskostnaderna i staden, dels för att den inte ens inbringade särskilt mycket. Hälsocentralerna används närmast av småbarnsfamiljer, dem som sköter hem och familj, pensionärer och arbetslösa. De som är ute i arbetslivet har tillgång till kostnadsfri arbetsplatshälsovård.",
      "explanation_en": null,
      "explanation_ru": null,
      "explanation_sme": null,
      "explanation_ara": null,
      "explanation_ukr": null,
      "explanation_som": null
    },
    "241": {
      "answer": 1,
      "options_answer": null,
      "explanation_fi": null,
      "explanation_sv": "Jämlikhet får inte innebära en allmän tillplattning av ubildningen.",
      "explanation_en": null,
      "explanation_ru": null,
      "explanation_sme": null,
      "explanation_ara": null,
      "explanation_ukr": null,
      "explanation_som": null
    },
    "242": {
      "answer": 5,
      "options_answer": null,
      "explanation_fi": null,
      "explanation_sv": "Det gör vi redan, och bör effektivera det. Samhället är inte betjänt av marginalisering, segregation, utanförskap, utslagning, gängbildning och ökad kriminalitet.",
      "explanation_en": null,
      "explanation_ru": null,
      "explanation_sme": null,
      "explanation_ara": null,
      "explanation_ukr": null,
      "explanation_som": null
    },
    "243": {
      "answer": 4,
      "options_answer": null,
      "explanation_fi": null,
      "explanation_sv": "HRT utreder som bäst olika alternativ för att öka kollektivtrafikens attraktionskraft, och en A-zonsbiljett kunde vara ett recept också för att vitalisera stadskärnan.",
      "explanation_en": null,
      "explanation_ru": null,
      "explanation_sme": null,
      "explanation_ara": null,
      "explanation_ukr": null,
      "explanation_som": null
    },
    "244": {
      "answer": 4,
      "options_answer": null,
      "explanation_fi": null,
      "explanation_sv": "Helst jo, men köptjänster bör inte uteslutas om de är mer rationella.",
      "explanation_en": null,
      "explanation_ru": null,
      "explanation_sme": null,
      "explanation_ara": null,
      "explanation_ukr": null,
      "explanation_som": null
    },
    "245": {
      "answer": 4,
      "options_answer": null,
      "explanation_fi": null,
      "explanation_sv": "Jo, men för arrendetomter betalas ju ingen fastighetsskatt, så man bör se till helhetsresultatet.",
      "explanation_en": null,
      "explanation_ru": null,
      "explanation_sme": null,
      "explanation_ara": null,
      "explanation_ukr": null,
      "explanation_som": null
    }
  },
  "mediapartnerAnswers": {
    "45": {
      "answer": 5,
      "explanation_fi": null,
      "explanation_sv": "Inhemskt och näproducerat är också hälsosammare.",
      "explanation_en": null,
      "explanation_ru": null,
      "explanation_sme": null,
      "explanation_ara": null,
      "explanation_ukr": null,
      "explanation_som": null
    },
    "46": {
      "answer": 2,
      "explanation_fi": null,
      "explanation_sv": "I Helsingfors har vi inte skog som skulle motivera aktivt skogsbruk, men vårdande, förstås.",
      "explanation_en": null,
      "explanation_ru": null,
      "explanation_sme": null,
      "explanation_ara": null,
      "explanation_ukr": null,
      "explanation_som": null
    },
    "57": {
      "answer": 2,
      "explanation_fi": null,
      "explanation_sv": "Vi kunde bygga ut vindkraft i havet, närmast utanför Nordsjö hamn.",
      "explanation_en": null,
      "explanation_ru": null,
      "explanation_sme": null,
      "explanation_ara": null,
      "explanation_ukr": null,
      "explanation_som": null
    },
    "59": {
      "answer": 5,
      "explanation_fi": null,
      "explanation_sv": "Tietysti!",
      "explanation_en": null,
      "explanation_ru": null,
      "explanation_sme": null,
      "explanation_ara": null,
      "explanation_ukr": null,
      "explanation_som": null
    },
    "62": {
      "answer": null,
      "explanation_fi": null,
      "explanation_sv": "En pysty ottamaan kantaa, näin Helsingin horisontilta.",
      "explanation_en": null,
      "explanation_ru": null,
      "explanation_sme": null,
      "explanation_ara": null,
      "explanation_ukr": null,
      "explanation_som": null
    }
  },
  "video_description_fi": null,
  "video_description_sv": null,
  "video_description_en": null,
  "video_description_ru": null,
  "video_description_sme": null,
  "video_description_ara": null,
  "candidate_hidden": null,
  "info": {
    "left_right_axis": {
      "id": 45,
      "background_info_id": 10,
      "name_fi": "En vasemmalle enkä oikealle",
      "name_sv": "Varken vänster eller höger",
      "name_en": "Neither to the right or the left",
      "name_ru": "Ни слева, ни справа",
      "name_sme": "In gurut inge olgeš guvlui",
      "name_ara": "لا إلى اليسار ولا إلى اليمين",
      "target_value": 0,
      "name_ukr": null,
      "name_som": null
    },
    "election_promise_3": {
      "fi": null,
      "se": "Jag gör mitt bästa för att bevara och stärka Helsingfors som en tvåspråkig stad, öppen för olika kulturer och därmed mångfald. Det handlar förutom om identitet och trivsel ocksä om konkurrenskraft då det gäller att locka investeringar och den arbetskraft vi behöver.",
      "en": null,
      "ru": null,
      "sme": null,
      "ara": null,
      "ukr": null,
      "som": null
    },
    "age": 1952,
    "language_skills": [
      {
        "fi": "suomi",
        "se": "finska",
        "en": "Finnish",
        "ru": "финский",
        "sme": "suomagiella",
        "ara": "الفنلندية"
      },
      {
        "fi": "ruotsi",
        "se": "svenska",
        "en": "Swedish",
        "ru": "шведский",
        "sme": "ruoŧagiella",
        "ara": "السويدية"
      },
      {
        "fi": "englanti",
        "se": "engelska",
        "en": "English",
        "ru": "английский",
        "sme": "eaŋgalsgiella",
        "ara": "الإنجليزية"
      },
      {
        "fi": "saksa",
        "se": "tyska",
        "en": "German",
        "ru": "немецкий",
        "sme": "duiskkagiella",
        "ara": "الألمانية"
      }
    ],
    "education": {
      "id": 51,
      "background_info_id": 16,
      "name_fi": "ylioppilas",
      "name_sv": "student",
      "name_en": "High school graduate",
      "name_ru": "выпускник лицея",
      "name_sme": "studeanta",
      "name_ara": "شهادة البكالوريا",
      "target_value": 3,
      "name_ukr": "випускник ліцею",
      "name_som": null
    },
    "gender": {
      "id": 19,
      "background_info_id": 6,
      "name_fi": "mies",
      "name_sv": "man",
      "name_en": "man",
      "name_ru": "Мужской",
      "name_sme": "almmái",
      "name_ara": "رجل",
      "target_value": null,
      "name_ukr": "Чоловіча",
      "name_som": "nin"
    },
    "lifevalues": {
      "fi": "Liberaali, demokraatti, sosiaalinen, humaani, perhekeskeinen",
      "se": "Liberal, demokrat, social, human, familjeorienterad",
      "en": null,
      "ru": null,
      "sme": null,
      "ara": null,
      "ukr": null,
      "som": null
    },
    "election_promise_2": {
      "fi": null,
      "se": "Att göra mitt bästa för att staden ska kunna erbjuda den service invånarna behöver, såsom dagvård i mindre grupper och daghem, kvalitativt högtstående undervisning i skolor med egna klassrum, ett rikt kulturutbud för alla åldrar och olika smaker, en fungerande och förmånlig kollektvtrafik i harmoni med en smidig privatbilstrafik utan onödiga förbud, en fungerande hälso- och sjukvård utan orimligt köande och en heltäckande äldrevård för alla, från hemservice till en mänsklig dygnetruntvård för dem som behöver den. Och allt självfallet på bägge nationalspråken finska och svenska, och vid behov andra språk.",
      "en": null,
      "ru": null,
      "sme": null,
      "ara": null,
      "ukr": null,
      "som": null
    },
    "language": {
      "id": 23,
      "background_info_id": 8,
      "name_fi": "ruotsi",
      "name_sv": "Svenska",
      "name_en": "Swedish",
      "name_ru": "шведский",
      "name_sme": "ruoŧagiella",
      "name_ara": "السويدية",
      "target_value": null,
      "name_ukr": "шведська",
      "name_som": "af-Iswiidhish"
    },
    "homepage_url": "http://bjornmansson.fi",
    "facebook_url": "https://www.facebook.com/bjorn.mansson.3",
    "language_some_other": {
      "fi": null,
      "se": "lite ryska, efter två års studier vid Hanken",
      "en": null,
      "ru": "lite ryska, efter två års studier vid Hanken",
      "sme": null,
      "ara": null,
      "ukr": null,
      "som": null
    },
    "municipality_fix": {
      "fi": "Katso vaalilupaukseni!",
      "se": "Se mina vallöften!",
      "en": null,
      "ru": null,
      "sme": null,
      "ara": null,
      "ukr": null,
      "som": null
    },
    "representative_other": {
      "fi": null,
      "se": "Ordförande för stadens naionalspråksnämnd med rätt att delta i stadsstyrelsens möten då social-, hälsovårds- och räddningsärenden behandlas, medlem av social-, hälsovårds- och räddningsnämnden, medlem av Helsingfors regiontrafiks styrelse, medlem av Kommunförbundets förbundsfullmäktige och svenska delegation, medlem av Nylads landskapsfullmäktige. Tidigare bl.a. medlem av styrelsen för HUS.",
      "en": null,
      "ru": null,
      "sme": null,
      "ara": null,
      "ukr": null,
      "som": null
    },
    "liberal_conservative_axis": {
      "id": 2,
      "background_info_id": 2,
      "name_fi": "Liberaali",
      "name_sv": "Liberal",
      "name_en": "Liberal",
      "name_ru": "Либерал",
      "name_sme": "Liberála",
      "name_ara": "ليبرالي",
      "target_value": -2,
      "name_ukr": null,
      "name_som": null
    },
    "municipality": "091",
    "language_other": {
      "fi": null,
      "se": "Finska genom äktenskap..",
      "en": null,
      "ru": null,
      "sme": null,
      "ara": null,
      "ukr": null,
      "som": null
    },
    "election_promise_1": {
      "fi": null,
      "se": "Att göra mitt bästa för att bevara så mycket som möjligt av Helsingfors karaktär som en trivsam stad för alla invånare, genom att bevara parker, naturområden, öppna platser och byggda kulturmiljöer. Vi får inte bygga hela staden full med bostads- och kontorshus, inte riva gamla byggnader som kan bevaras och inte fördärva stadsdelarnas prägel och karaktär genom ohejdat kompletteringsbyggande.",
      "en": null,
      "ru": null,
      "sme": null,
      "ara": null,
      "ukr": null,
      "som": null
    },
    "representative": [
      {
        "fi": "kunnanvaltuutettu",
        "se": "ledamot i kommunfullmäktige",
        "en": "municipal councillor",
        "ru": null,
        "sme": null,
        "ara": null
      }
    ],
    "political_experience": {
      "fi": null,
      "se": "Gen.sekr. för Svenska riksdagsguppen 2009-2013",
      "en": null,
      "ru": null,
      "sme": null,
      "ara": null,
      "ukr": null,
      "som": null
    }
  }
}
