{
  "id": 18112,
  "first_name": "Clas-Håkan",
  "last_name": "Nyman",
  "election_number": 653,
  "party_id": 8,
  "image": "kuvat/akv2025/18112/c588b8cd-89b8-46bf-98d6-c30f661957f9",
  "constituency_id": 25,
  "video": null,
  "video_aspect": null,
  "answers": {
    "81": {
      "answer": 5,
      "options_answer": null,
      "explanation_fi": null,
      "explanation_sv": null,
      "explanation_en": null,
      "explanation_ru": null,
      "explanation_sme": null,
      "explanation_ara": null,
      "explanation_ukr": null,
      "explanation_som": null
    },
    "82": {
      "answer": 5,
      "options_answer": null,
      "explanation_fi": null,
      "explanation_sv": null,
      "explanation_en": null,
      "explanation_ru": null,
      "explanation_sme": null,
      "explanation_ara": null,
      "explanation_ukr": null,
      "explanation_som": null
    },
    "83": {
      "answer": 2,
      "options_answer": null,
      "explanation_fi": null,
      "explanation_sv": null,
      "explanation_en": null,
      "explanation_ru": null,
      "explanation_sme": null,
      "explanation_ara": null,
      "explanation_ukr": null,
      "explanation_som": null
    },
    "84": {
      "answer": 1,
      "options_answer": null,
      "explanation_fi": null,
      "explanation_sv": null,
      "explanation_en": null,
      "explanation_ru": null,
      "explanation_sme": null,
      "explanation_ara": null,
      "explanation_ukr": null,
      "explanation_som": null
    },
    "85": {
      "answer": 5,
      "options_answer": null,
      "explanation_fi": null,
      "explanation_sv": null,
      "explanation_en": null,
      "explanation_ru": null,
      "explanation_sme": null,
      "explanation_ara": null,
      "explanation_ukr": null,
      "explanation_som": null
    },
    "86": {
      "answer": 2,
      "options_answer": null,
      "explanation_fi": null,
      "explanation_sv": "i dagens mångkulturella samhälle måste häsyn tas även till andra kulturer och religioner. Livsåskådning borde prioriteras i skolorna.",
      "explanation_en": null,
      "explanation_ru": null,
      "explanation_sme": null,
      "explanation_ara": null,
      "explanation_ukr": null,
      "explanation_som": null
    },
    "87": {
      "answer": 4,
      "options_answer": null,
      "explanation_fi": null,
      "explanation_sv": null,
      "explanation_en": null,
      "explanation_ru": null,
      "explanation_sme": null,
      "explanation_ara": null,
      "explanation_ukr": null,
      "explanation_som": null
    },
    "88": {
      "answer": 2,
      "options_answer": null,
      "explanation_fi": null,
      "explanation_sv": "Man bör eftersträva en jämvikt i utbud och efterfrågan. Vissa tjänster kan man kanske utlokalisera men inte till vilket pris som helst.",
      "explanation_en": null,
      "explanation_ru": null,
      "explanation_sme": null,
      "explanation_ara": null,
      "explanation_ukr": null,
      "explanation_som": null
    },
    "89": {
      "answer": 1,
      "options_answer": null,
      "explanation_fi": null,
      "explanation_sv": "Alla bör delta i kostnaderna för kommunen.",
      "explanation_en": null,
      "explanation_ru": null,
      "explanation_sme": null,
      "explanation_ara": null,
      "explanation_ukr": null,
      "explanation_som": null
    },
    "90": {
      "answer": 5,
      "options_answer": null,
      "explanation_fi": null,
      "explanation_sv": "Klart att här skall gälla förnuft i handlandet. Om kommunen inte förmår producera till vettigt pris måste tjänsten upphandlas av andra.",
      "explanation_en": null,
      "explanation_ru": null,
      "explanation_sme": null,
      "explanation_ara": null,
      "explanation_ukr": null,
      "explanation_som": null
    },
    "91": {
      "answer": 4,
      "options_answer": null,
      "explanation_fi": null,
      "explanation_sv": null,
      "explanation_en": null,
      "explanation_ru": null,
      "explanation_sme": null,
      "explanation_ara": null,
      "explanation_ukr": null,
      "explanation_som": null
    },
    "92": {
      "answer": 1,
      "options_answer": null,
      "explanation_fi": null,
      "explanation_sv": "De kan finnas orsaker att få en mera nära och personlig betjäningsom an föda ett nytänkande.\nKräver rätt mycket av tjänstemannen. Bör vara empatisk och verkligen sätta sig in siyuationen",
      "explanation_en": null,
      "explanation_ru": null,
      "explanation_sme": null,
      "explanation_ara": null,
      "explanation_ukr": null,
      "explanation_som": null
    },
    "93": {
      "answer": 1,
      "options_answer": null,
      "explanation_fi": null,
      "explanation_sv": "Tvång är aldrig bra. Leder till missnöje.",
      "explanation_en": null,
      "explanation_ru": null,
      "explanation_sme": null,
      "explanation_ara": null,
      "explanation_ukr": null,
      "explanation_som": null
    },
    "94": {
      "answer": 5,
      "options_answer": null,
      "explanation_fi": null,
      "explanation_sv": "Kultur i alla former är viktigt för själen.",
      "explanation_en": null,
      "explanation_ru": null,
      "explanation_sme": null,
      "explanation_ara": null,
      "explanation_ukr": null,
      "explanation_som": null
    },
    "95": {
      "answer": 4,
      "options_answer": null,
      "explanation_fi": null,
      "explanation_sv": null,
      "explanation_en": null,
      "explanation_ru": null,
      "explanation_sme": null,
      "explanation_ara": null,
      "explanation_ukr": null,
      "explanation_som": null
    },
    "96": {
      "answer": 5,
      "options_answer": null,
      "explanation_fi": null,
      "explanation_sv": "Bara genom att förstå varandra an man leva i samförstånd. Det är viktigt med öppenhet och möjligheter\ntill att umgås.",
      "explanation_en": null,
      "explanation_ru": null,
      "explanation_sme": null,
      "explanation_ara": null,
      "explanation_ukr": null,
      "explanation_som": null
    },
    "97": {
      "answer": 5,
      "options_answer": null,
      "explanation_fi": null,
      "explanation_sv": "Enligt mig gör Helsingfors redan detta ganska bra.",
      "explanation_en": null,
      "explanation_ru": null,
      "explanation_sme": null,
      "explanation_ara": null,
      "explanation_ukr": null,
      "explanation_som": null
    },
    "98": {
      "answer": 5,
      "options_answer": null,
      "explanation_fi": null,
      "explanation_sv": null,
      "explanation_en": null,
      "explanation_ru": null,
      "explanation_sme": null,
      "explanation_ara": null,
      "explanation_ukr": null,
      "explanation_som": null
    },
    "99": {
      "answer": 2,
      "options_answer": null,
      "explanation_fi": null,
      "explanation_sv": null,
      "explanation_en": null,
      "explanation_ru": null,
      "explanation_sme": null,
      "explanation_ara": null,
      "explanation_ukr": null,
      "explanation_som": null
    },
    "100": {
      "answer": 2,
      "options_answer": null,
      "explanation_fi": null,
      "explanation_sv": null,
      "explanation_en": null,
      "explanation_ru": null,
      "explanation_sme": null,
      "explanation_ara": null,
      "explanation_ukr": null,
      "explanation_som": null
    },
    "101": {
      "answer": 1,
      "options_answer": null,
      "explanation_fi": null,
      "explanation_sv": "Naturen behövs och alla parker behöver inte bebyggas.",
      "explanation_en": null,
      "explanation_ru": null,
      "explanation_sme": null,
      "explanation_ara": null,
      "explanation_ukr": null,
      "explanation_som": null
    },
    "102": {
      "answer": 5,
      "options_answer": null,
      "explanation_fi": null,
      "explanation_sv": null,
      "explanation_en": null,
      "explanation_ru": null,
      "explanation_sme": null,
      "explanation_ara": null,
      "explanation_ukr": null,
      "explanation_som": null
    },
    "103": {
      "answer": 5,
      "options_answer": null,
      "explanation_fi": null,
      "explanation_sv": "det är bevisat att Finland och Helsingfors behöver invandring för att fylla arbetsplatsbehovet på lång sikt.\nVi behöver skattebetalare och arbetstagare.",
      "explanation_en": null,
      "explanation_ru": null,
      "explanation_sme": null,
      "explanation_ara": null,
      "explanation_ukr": null,
      "explanation_som": null
    },
    "104": {
      "answer": 1,
      "options_answer": null,
      "explanation_fi": null,
      "explanation_sv": "Relaterande fråga till ovanstående. Smakar det så kostar det. Fel ställe att spara på.",
      "explanation_en": null,
      "explanation_ru": null,
      "explanation_sme": null,
      "explanation_ara": null,
      "explanation_ukr": null,
      "explanation_som": null
    },
    "105": {
      "answer": 1,
      "options_answer": null,
      "explanation_fi": null,
      "explanation_sv": "Se föregående fråga.",
      "explanation_en": null,
      "explanation_ru": null,
      "explanation_sme": null,
      "explanation_ara": null,
      "explanation_ukr": null,
      "explanation_som": null
    },
    "238": {
      "answer": 1,
      "options_answer": null,
      "explanation_fi": null,
      "explanation_sv": "Visst bör något göras för att få ned utsläppen i innerstaden men inte genom förbud.\nByggandet av den omtalade centrum tunneln vore ett bra alternativ.",
      "explanation_en": null,
      "explanation_ru": null,
      "explanation_sme": null,
      "explanation_ara": null,
      "explanation_ukr": null,
      "explanation_som": null
    },
    "239": {
      "answer": 5,
      "options_answer": null,
      "explanation_fi": null,
      "explanation_sv": "All form övertramp, extremistiska rörelser borde totalt förbjudas och inte uppmuntras.",
      "explanation_en": null,
      "explanation_ru": null,
      "explanation_sme": null,
      "explanation_ara": null,
      "explanation_ukr": null,
      "explanation_som": null
    },
    "240": {
      "answer": 4,
      "options_answer": null,
      "explanation_fi": null,
      "explanation_sv": "Om en avgift hjälper hälsovården till högre och bättre service är det rätt väg att gå.\nDock borde en eventuell avgift vara justerbar så att den inte belastar alla på samma sätt. De mest utsatta bör ochså kunna anlita hälsovårdstjänster.",
      "explanation_en": null,
      "explanation_ru": null,
      "explanation_sme": null,
      "explanation_ara": null,
      "explanation_ukr": null,
      "explanation_som": null
    },
    "241": {
      "answer": 1,
      "options_answer": null,
      "explanation_fi": null,
      "explanation_sv": "Det är berikande för samhället och individen med undervisning som är speciellt riktad till barn med särintressen och färdigheter.",
      "explanation_en": null,
      "explanation_ru": null,
      "explanation_sme": null,
      "explanation_ara": null,
      "explanation_ukr": null,
      "explanation_som": null
    },
    "242": {
      "answer": 4,
      "options_answer": null,
      "explanation_fi": null,
      "explanation_sv": null,
      "explanation_en": null,
      "explanation_ru": null,
      "explanation_sme": null,
      "explanation_ara": null,
      "explanation_ukr": null,
      "explanation_som": null
    },
    "243": {
      "answer": 5,
      "options_answer": null,
      "explanation_fi": null,
      "explanation_sv": "Oskäligt att man för två hållplatser med spårvagn i innerstaden skall betala en AB biljett.",
      "explanation_en": null,
      "explanation_ru": null,
      "explanation_sme": null,
      "explanation_ara": null,
      "explanation_ukr": null,
      "explanation_som": null
    },
    "244": {
      "answer": 5,
      "options_answer": null,
      "explanation_fi": null,
      "explanation_sv": "Genom att koncentrera skolhälsovården till egna enheter tror jag att man får bättre koll och kan förebygga många problem i framtiden.",
      "explanation_en": null,
      "explanation_ru": null,
      "explanation_sme": null,
      "explanation_ara": null,
      "explanation_ukr": null,
      "explanation_som": null
    },
    "245": {
      "answer": 4,
      "options_answer": null,
      "explanation_fi": null,
      "explanation_sv": null,
      "explanation_en": null,
      "explanation_ru": null,
      "explanation_sme": null,
      "explanation_ara": null,
      "explanation_ukr": null,
      "explanation_som": null
    }
  },
  "mediapartnerAnswers": {
    "45": {
      "answer": 5,
      "explanation_fi": null,
      "explanation_sv": null,
      "explanation_en": null,
      "explanation_ru": null,
      "explanation_sme": null,
      "explanation_ara": null,
      "explanation_ukr": null,
      "explanation_som": null
    },
    "46": {
      "answer": 4,
      "explanation_fi": null,
      "explanation_sv": null,
      "explanation_en": null,
      "explanation_ru": null,
      "explanation_sme": null,
      "explanation_ara": null,
      "explanation_ukr": null,
      "explanation_som": null
    },
    "57": {
      "answer": 4,
      "explanation_fi": null,
      "explanation_sv": null,
      "explanation_en": null,
      "explanation_ru": null,
      "explanation_sme": null,
      "explanation_ara": null,
      "explanation_ukr": null,
      "explanation_som": null
    },
    "59": {
      "answer": 5,
      "explanation_fi": null,
      "explanation_sv": null,
      "explanation_en": null,
      "explanation_ru": null,
      "explanation_sme": null,
      "explanation_ara": null,
      "explanation_ukr": null,
      "explanation_som": null
    },
    "62": {
      "answer": 4,
      "explanation_fi": null,
      "explanation_sv": "En tunne kumpaakaan kunnan tilannetta joten periaatteessa en voi ottaa kantaa.",
      "explanation_en": null,
      "explanation_ru": null,
      "explanation_sme": null,
      "explanation_ara": null,
      "explanation_ukr": null,
      "explanation_som": null
    }
  },
  "video_description_fi": null,
  "video_description_sv": null,
  "video_description_en": null,
  "video_description_ru": null,
  "video_description_sme": null,
  "video_description_ara": null,
  "candidate_hidden": null,
  "info": {
    "left_right_axis": {
      "id": 46,
      "background_info_id": 10,
      "name_fi": "Hieman oikealle",
      "name_sv": "Lite till Till högerhöger",
      "name_en": "SlightTo the rightly to the right",
      "name_ru": "Немного справа",
      "name_sme": "Vehá olgeš guvlui",
      "name_ara": "أميل إلى اليمين",
      "target_value": 1,
      "name_ukr": null,
      "name_som": null
    },
    "election_promise_3": {
      "fi": null,
      "se": "Planeringen i staden bör bygga på en hållbart och trivsamt miljövänligt byggande. ",
      "en": null,
      "ru": null,
      "sme": null,
      "ara": null,
      "ukr": null,
      "som": null
    },
    "age": 1953,
    "language_skills": [
      {
        "fi": "suomi",
        "se": "finska",
        "en": "Finnish",
        "ru": "финский",
        "sme": "suomagiella",
        "ara": "الفنلندية"
      },
      {
        "fi": "ruotsi",
        "se": "svenska",
        "en": "Swedish",
        "ru": "шведский",
        "sme": "ruoŧagiella",
        "ara": "السويدية"
      },
      {
        "fi": "englanti",
        "se": "engelska",
        "en": "English",
        "ru": "английский",
        "sme": "eaŋgalsgiella",
        "ara": "الإنجليزية"
      },
      {
        "fi": "joku muu",
        "se": "något annat",
        "en": "Other",
        "ru": "другой",
        "sme": "muhtin eará",
        "ara": "لغة أخرى"
      }
    ],
    "education": {
      "id": 52,
      "background_info_id": 16,
      "name_fi": "alempi korkeakoulututkinto",
      "name_sv": "lägre högskoleexamen",
      "name_en": "Bachelors degree",
      "name_ru": "первая ступень высшего образования (бакалавриат)",
      "name_sme": "vuolit allaskuvladutkkus",
      "name_ara": "درجة البكالوريوس",
      "target_value": 4,
      "name_ukr": "перший ступінь вищої освіти (бакалаврат)",
      "name_som": null
    },
    "gender": {
      "id": 19,
      "background_info_id": 6,
      "name_fi": "mies",
      "name_sv": "man",
      "name_en": "man",
      "name_ru": "Мужской",
      "name_sme": "almmái",
      "name_ara": "رجل",
      "target_value": null,
      "name_ukr": "Чоловіча",
      "name_som": "nin"
    },
    "lifevalues": {
      "fi": null,
      "se": "1. Ärlighet, man skall vara sanningsenlig och genomskinlig\n2.Respekt, behandla andra med med värdighet och hänsyn\n3. Ansvar, ta sitt ansvar för handlingar och beslut\n4.Frihet, värdesätta sjävständighet och valmöjligheter\n5. Gemenskap, prioritera samarbete och relationer",
      "en": null,
      "ru": null,
      "sme": null,
      "ara": null,
      "ukr": null,
      "som": null
    },
    "election_promise_2": {
      "fi": null,
      "se": "Jag vill verka för att vi har välmående invånare i Helsingfors och att man får service på svenska.",
      "en": null,
      "ru": null,
      "sme": null,
      "ara": null,
      "ukr": null,
      "som": null
    },
    "language": {
      "id": 23,
      "background_info_id": 8,
      "name_fi": "ruotsi",
      "name_sv": "Svenska",
      "name_en": "Swedish",
      "name_ru": "шведский",
      "name_sme": "ruoŧagiella",
      "name_ara": "السويدية",
      "target_value": null,
      "name_ukr": "шведська",
      "name_som": "af-Iswiidhish"
    },
    "language_some_other": {
      "fi": null,
      "se": "Danska och norska behärskar jag rätt bra då jobbat i danskt företag i tiotalsår.",
      "en": null,
      "ru": null,
      "sme": null,
      "ara": null,
      "ukr": null,
      "som": null
    },
    "municipality_fix": {
      "fi": null,
      "se": "Utvecklandet av östra Helsingfors i synnerhet Östersundom bör prioriteras och komma igång.\nPlaner finns och har visats upp på invånarkvällar men ingenting händer! -Byn \"dör\" bort.\nFolk flyttar ut men ingen in då man inte kan bygga då plan saknas och det råder byggförbud.\nAllt pga. distributörerna för områdets vattenförsörjning inte kan komma överens infrastukturens värde (vattenrören) enligt planerarna.",
      "en": null,
      "ru": null,
      "sme": null,
      "ara": null,
      "ukr": null,
      "som": null
    },
    "representative_other": {
      "fi": null,
      "se": "För tillfället har jag inga förtroendeuppdrag men har en historia som kommunalpolitiker i Sibbo där jag suttit i såväl fullmäktige som kommunstyrelsen, i social och hälsovårdsnämden samt individsektionen.\nHar även fungerat som ordförande i Sibbo Servicehus Stiftelse.\n",
      "en": null,
      "ru": null,
      "sme": null,
      "ara": null,
      "ukr": null,
      "som": null
    },
    "liberal_conservative_axis": {
      "id": 3,
      "background_info_id": 2,
      "name_fi": "Hieman liberaali",
      "name_sv": "Ganska liberal",
      "name_en": "Slightly liberal",
      "name_ru": "Слегка либерал",
      "name_sme": "Vehá liberála",
      "name_ara": "أميل إلى الليبرالية",
      "target_value": -1,
      "name_ukr": null,
      "name_som": null
    },
    "municipality": "091",
    "election_promise_1": {
      "fi": null,
      "se": "För utveckling av östra Helsingfors med betoning på Östersundom.\nBoendet och byggandet bör ske på invånarnas villkor",
      "en": null,
      "ru": null,
      "sme": null,
      "ara": null,
      "ukr": null,
      "som": null
    },
    "representative": [
      {
        "fi": "ei mikään näistä",
        "se": "inget av dessa",
        "en": "none of the above",
        "ru": null,
        "sme": null,
        "ara": null
      }
    ],
    "political_experience": {
      "fi": null,
      "se": "Som tidigare nämt. tolv år i Sibbo kommun. Såväl i kommunfullmäktige som styrelse och social och hälsovårds nämden. Ordförande i Sibbo Servicehus Stiftelse.",
      "en": null,
      "ru": null,
      "sme": null,
      "ara": null,
      "ukr": null,
      "som": null
    }
  }
}
